[
{ "id": 1, "name": "Aswini", "display_name": "Aswini_Mesham", "full_name": "Aswini" },
{ "id": 2, "name": "Barani", "display_name": "Barani_Mesham", "full_name": "Barani" },
{ "id": 3, "name": "Karthigai_1", "display_name": "Karthigai_Mesham", "full_name": "Karthigai (Pada 1)" },
{ "id": 4, "name": "Karthigai_234", "display_name": "Karthigai_Rishabam", "full_name": "Karthigai (Pada 2,3,4)" },
{ "id": 5, "name": "Rohini", "display_name": "Rohini_Rishabam", "full_name": "Rohini" },
{ "id": 6, "name": "Mirug_12", "display_name": "Mirugasirisham_Rishabam", "full_name": "Mrigasira (Pada 1,2)" },
{ "id": 7, "name": "Mirug_34", "display_name": "Mirugasirisham_Mithunam", "full_name": "Mrigasira (Pada 3,4)" },
{ "id": 8, "name": "Thiruvathirai", "display_name": "Thiruvathirai_Mithunam", "full_name": "Thiruvathirai (Ardra)" },
{ "id": 9, "name": "Punar_123", "display_name": "Punarpoosam_Mithunam", "full_name": "Punarvasu (Pada 1,2,3)" },
{ "id": 10, "name": "Punar_4", "display_name": "Punarpoosam_Kadagam", "full_name": "Punarvasu (Pada 4)" },
{ "id": 11, "name": "Poosam", "display_name": "Poosam_Kadagam", "full_name": "Poosam (Pushya)" },
{ "id": 12, "name": "Ayilyam", "display_name": "Ayilyam_Kadagam", "full_name": "Ayilyam (Ashlesha)" },
{ "id": 13, "name": "Magam", "display_name": "Magam_Simham", "full_name": "Magam (Magha)" },
{ "id": 14, "name": "Pooram", "display_name": "Pooram_Simham", "full_name": "Pooram (Purva Phalguni)" },
{ "id": 15, "name": "Uthiram_1", "display_name": "Uthiram_Simham", "full_name": "Uthiram (Pada 1)" },
{ "id": 16, "name": "Uthiram_234", "display_name": "Uthiram_Kanni", "full_name": "Uthiram (Pada 2,3,4)" },
{ "id": 17, "name": "Hastham", "display_name": "Hastham_Kanni", "full_name": "Hastham (Hasta)" },
{ "id": 18, "name": "Chithirai_12", "display_name": "Chithirai_Kanni", "full_name": "Chithirai (Pada 1,2)" },
{ "id": 19, "name": "Chithirai_34", "display_name": "Chithirai_Thulam", "full_name": "Chithirai (Pada 3,4)" },
{ "id": 20, "name": "Swathi", "display_name": "Swathi_Thulam", "full_name": "Swathi" },
{ "id": 21, "name": "Visagam_123", "display_name": "Visagam_Thulam", "full_name": "Visagam (Pada 1,2,3)" },
{ "id": 22, "name": "Visagam_4", "display_name": "Visagam_Viruchigam", "full_name": "Visagam (Pada 4)" },
{ "id": 23, "name": "Anusam", "display_name": "Anusam_Viruchigam", "full_name": "Anusam (Anuradha)" },
{ "id": 24, "name": "Ketai", "display_name": "Ketai_Viruchigam", "full_name": "Ketai (Jyeshtha)" },
{ "id": 25, "name": "Moolam", "display_name": "Moolam_Dhanusu", "full_name": "Moolam (Mula)" },
{ "id": 26, "name": "Pooradam", "display_name": "Pooradam_Dhanusu", "full_name": "Pooradam (Purva Ashadha)" },
{ "id": 27, "name": "Uthi_1", "display_name": "Uthiradam_Dhanusu", "full_name": "Utharaadam (Pada 1)" },
{ "id": 28, "name": "Uthi_234", "display_name": "Uthiradam_Magaram", "full_name": "Utharaadam (Pada 2,3,4)" },
{ "id": 29, "name": "Thiruvonam", "display_name": "Thiruvonam_Magaram", "full_name": "Thiruvonam (Shravana)" },
{ "id": 30, "name": "Avitam_12", "display_name": "Avitam_Magaram", "full_name": "Avitam (Pada 1,2)" },
{ "id": 31, "name": "Avitam_34", "display_name": "Avitam_Kumbham", "full_name": "Avitam (Pada 3,4)" },
{ "id": 32, "name": "Sadayam", "display_name": "Sadayam_Kumbham", "full_name": "Sadayam (Shatabhisha)" },
{ "id": 33, "name": "Poortathi_123", "display_name": "Pooratathi_Kumbham", "full_name": "Poortathi (Pada 1,2,3)" },
{ "id": 34, "name": "Poortathi_4", "display_name": "Poortathi_Meenam", "full_name": "Poortathi (Pada 4)" },
{ "id": 35, "name": "Uthiratathi", "display_name": "Uthiratathi_Meenam", "full_name": "Uthiratathi (Uttara Bhadrapada)" },
{ "id": 36, "name": "Revathi", "display_name": "Revathi_Meenam", "full_name": "Revathi" }
]